{
  "parties": [
    {
      "start_date": "2004-06-28",
      "name_en": "Conservative Party of Canada",
      "name_fr": "Parti conservateur du Canada"
    }
  ],
  "date_of_birth": "1951-10-05",
  "place_of_birth": {
    "name_en": "Esterhazy, Saskatchewan, Canada",
    "name_fr": "Esterhazy, Saskatchewan, Canada"
  },
  "name": "Tom Lukiwski",
  "functions": [
    {
      "role_en": "Parliamentary Secretary",
      "start_date": "2008-11-07",
      "role_fr": "Secr\u00e9taire parlementaire",
      "title_en": "Parliamentary Secretary to the Leader of the Government in the House of Commons",
      "title_fr": "Secr\u00e9taire parlementaire du leader du gouvernement \u00e0 la Chambre des communes"
    },
    {
      "role_en": "Parliamentary Secretary",
      "start_date": "2006-02-07",
      "role_fr": "Secr\u00e9taire parlementaire",
      "end_date": "2008-11-06",
      "title_en": "Parliamentary Secretary to the Leader of the Government in the House of Commons and Minister for Democratic Reform",
      "title_fr": "Secr\u00e9taire parlementaire du leader du gouvernement \u00e0 la Chambre des communes et ministre de la r\u00e9forme d\u00e9mocratique"
    }
  ],
  "committees": [
    {
      "role_en": "Member",
      "role_fr": "Membre",
      "parliament": 40,
      "session": 3,
      "name_en": "Standing Committee on Procedure and House Affairs",
      "name_fr": "Comit\u00e9 permanent de la proc\u00e9dure et des affaires de la Chambre"
    },
    {
      "role_en": "Member",
      "role_fr": "Membre",
      "parliament": 40,
      "session": 2,
      "name_en": "Standing Committee on Procedure and House Affairs",
      "name_fr": "Comit\u00e9 permanent de la proc\u00e9dure et des affaires de la Chambre"
    },
    {
      "role_en": "Member",
      "role_fr": "Membre",
      "parliament": 40,
      "session": 1,
      "name_en": "Standing Committee on Procedure and House Affairs",
      "name_fr": "Comit\u00e9 permanent de la proc\u00e9dure et des affaires de la Chambre"
    },
    {
      "role_en": "Member",
      "role_fr": "Membre",
      "parliament": 39,
      "session": 2,
      "name_en": "Legislative Committee on Bill C-20",
      "name_fr": "Comit\u00e9 l\u00e9gislatif charg\u00e9 du projet de loi C-20"
    },
    {
      "role_en": "Member",
      "role_fr": "Membre",
      "parliament": 39,
      "session": 2,
      "name_en": "Standing Committee on Procedure and House Affairs",
      "name_fr": "Comit\u00e9 permanent de la proc\u00e9dure et des affaires de la Chambre"
    },
    {
      "role_en": "Member",
      "role_fr": "Membre",
      "parliament": 39,
      "session": 2,
      "name_en": "Subcommittee on Agenda and Procedure of the Legislative Committee on Bill C-20",
      "name_fr": "Sous-comit\u00e9 du programme et de la proc\u00e9dure du Comit\u00e9 l\u00e9gislatif charg\u00e9 du projet de loi C-20"
    },
    {
      "role_en": "Member",
      "role_fr": "Membre",
      "parliament": 39,
      "session": 1,
      "name_en": "Legislative Committee on Bill C-2",
      "name_fr": "Comit\u00e9 l\u00e9gislatif charg\u00e9 du projet de loi C-2"
    },
    {
      "role_en": "Member",
      "role_fr": "Membre",
      "parliament": 39,
      "session": 1,
      "name_en": "Legislative Committee on Bill C-27",
      "name_fr": "Comit\u00e9 l\u00e9gislatif charg\u00e9 du projet de loi C-27"
    },
    {
      "role_en": "Member",
      "role_fr": "Membre",
      "parliament": 39,
      "session": 1,
      "name_en": "Standing Committee on Procedure and House Affairs",
      "name_fr": "Comit\u00e9 permanent de la proc\u00e9dure et des affaires de la Chambre"
    },
    {
      "role_en": "Member",
      "role_fr": "Membre",
      "parliament": 38,
      "session": 1,
      "name_en": "Standing Committee on Access to Information, Privacy and Ethics",
      "name_fr": "Comit\u00e9 permanent de l'acc\u00e8s \u00e0 l'information, de la protection des renseignements personnels et de l'\u00e9thique"
    }
  ],
  "language": "English",
  "professions": [
    {
      "name_en": "Businessman",
      "name_fr": "Administrateur politique"
    },
    {
      "name_en": "Political administrator",
      "name_fr": "Homme d'affaires"
    }
  ],
  "id": "fe517b95-bc62-4fe8-96aa-998994aefd48"
}